shadowtrackr/__init__.py
shadowtrackr-4.5.dist-info/LICENSE
shadowtrackr-4.5.dist-info/METADATA
shadowtrackr-4.5.dist-info/WHEEL
shadowtrackr-4.5.dist-info/top_level.txt
shadowtrackr-4.5.dist-info/RECORD
