Metadata-Version: 2.1
Name: shadowtrackr
Version: 4.5
Summary: A python API for ShadowTrackr
Home-page: https://github.com/shadowtrackr/python_API
Author: Bas van Schaik
Author-email: bas@shadowtrackr.com
License: MIT
License-File: LICENSE
Requires-Dist: requests
Requires-Dist: pillow
